Changelog.txt
LICENSE.txt
MANIFEST.in
description.txt
setup.cfg
setup.py
PyDisdrometer.egg-info/PKG-INFO
PyDisdrometer.egg-info/SOURCES.txt
PyDisdrometer.egg-info/dependency_links.txt
PyDisdrometer.egg-info/pbr.json
PyDisdrometer.egg-info/requires.txt
PyDisdrometer.egg-info/top_level.txt
docs/build/html/_sources/index.txt
docs/build/html/_sources/pydisdrometer.aux_readers.txt
docs/build/html/_sources/pydisdrometer.plot.txt
docs/build/html/_sources/pydisdrometer.txt
pydisdrometer/DSDProcessor.py
pydisdrometer/DSR.py
pydisdrometer/DropSizeDistribution.py
pydisdrometer/__init__.py
pydisdrometer/aux_readers/ARM_APU_reader.py
pydisdrometer/aux_readers/GPMApuWallopsRawReader.py
pydisdrometer/aux_readers/NASA_2DVD_reader.py
pydisdrometer/aux_readers/__init__.py
pydisdrometer/aux_readers/read_2ds.py
pydisdrometer/aux_readers/read_hvps.py
pydisdrometer/io/Image2DReader.py
pydisdrometer/io/JWDReader.py
pydisdrometer/io/ParsivelNasaGVReader.py
pydisdrometer/io/ParsivelReader.py
pydisdrometer/io/__init__.py
pydisdrometer/io/common.py
pydisdrometer/partition/__init__.py
pydisdrometer/partition/cs_partition.py
pydisdrometer/plot/__init__.py
pydisdrometer/plot/plot.py
pydisdrometer/utility/__init__.py
pydisdrometer/utility/configuration.py
pydisdrometer/utility/dielectric.py
pydisdrometer/utility/expfit.py
pydisdrometer/utility/metadata.json
pydisdrometer/utility/ts_utility.py