Metadata-Version: 1.1
Name: PyDisdrometer
Version: 0.1.15.1
Summary: Python Disdrometer Processing
Home-page: http://pypi.python.org/pypi/PyDisdrometer/
Author: Joseph C. Hardin, Nick Guy
Author-email: josephhardinee@gmail.com
License: LICENSE.txt
Platform: UNKNOWN
Classifier: Development Status :: 3 - Alpha
Classifier: Environment :: Console
